Metadata-Version: 1.0
Name: pipeline-storage-package-upload
Version: 0.0.2
Summary: Pipeline storage demo on how to upload to Artifactory
Home-page: UNKNOWN
Author: UNKNOWN
Author-email: UNKNOWN
License: UNKNOWN
Platform: UNKNOWN
